satlib/__init__.py
satlib/core.py
satlib/utils.py
sat_mnist_solver-1.0.0.dist-info/LICENSE
sat_mnist_solver-1.0.0.dist-info/METADATA
sat_mnist_solver-1.0.0.dist-info/WHEEL
sat_mnist_solver-1.0.0.dist-info/entry_points.txt
sat_mnist_solver-1.0.0.dist-info/top_level.txt
sat_mnist_solver-1.0.0.dist-info/RECORD
