Metadata-Version: 2.1
Name: sat-mnist-solver
Version: 1.0.0
Summary: A SAT solver-based approach to classifying MNIST dataset using SAT encodings
Home-page: https://github.com/savannahshannon/sat_mnist_solver
Author: Savannah Shannon
Author-email: savannahshannon@example.com
Classifier: Programming Language :: Python :: 3
Classifier: License :: OSI Approved :: MIT License
Classifier: Operating System :: OS Independent
Requires-Python: >=3.6
License-File: LICENSE
Requires-Dist: torch>=2.0.0
Requires-Dist: torchvision>=0.10.0
Requires-Dist: python-sat>=1.8.0
Requires-Dist: pysat>=3.0.0
Provides-Extra: dev
Requires-Dist: pytest>=6.0; extra == "dev"
Requires-Dist: unittest; extra == "dev"
